lazy_py2neo.py
lazy_py2neo-2019.3.7.dist-info/LICENSE
lazy_py2neo-2019.3.7.dist-info/METADATA
lazy_py2neo-2019.3.7.dist-info/WHEEL
lazy_py2neo-2019.3.7.dist-info/top_level.txt
lazy_py2neo-2019.3.7.dist-info/RECORD
