Metadata-Version: 1.0
Name: lazy-py2neo
Version: 2019.3.7
Summary: # lazy_py2neo
